{
    "results":  [
                    {
                        "url":  "https://www.okx.com/api/v5/market/ticker?instId=BTC-USDT",
                        "data_ok":  false,
                        "latency_ok":  true,
                        "json_ok":  false,
                        "http_ok":  false,
                        "category":  "crypto",
                        "latency_ms":  70,
                        "error":  "The remote name could not be resolved: \u0027www.okx.com\u0027",
                        "critical":  true,
                        "name":  "okx_btc",
                        "healthy":  false
                    },
                    {
                        "url":  "https://api.binance.com/api/v3/ticker/price?symbol=BTCUSDT",
                        "data_ok":  false,
                        "latency_ok":  false,
                        "json_ok":  false,
                        "http_ok":  false,
                        "category":  "crypto",
                        "latency_ms":  5105,
                        "error":  "The operation has timed out.",
                        "critical":  true,
                        "name":  "binance_btc",
                        "healthy":  false
                    },
                    {
                        "url":  "https://min-api.cryptocompare.com/data/price?fsym=BTC\u0026tsyms=USD",
                        "data_ok":  false,
                        "latency_ok":  true,
                        "json_ok":  false,
                        "http_ok":  false,
                        "category":  "crypto",
                        "latency_ms":  584,
                        "error":  "{\"Data\":{},\"Err\":{\"type\":2,\"message\":\"API key required, please refer to the documentation at https://developers.coindesk.com/\",\"http_status_code\":401,\"frontend\":{\"type\":2,\"message\":\"API key required, please refer to the documentation at https://developers.coindesk.com/\"}}}",
                        "critical":  false,
                        "name":  "cryptocompare_btc",
                        "healthy":  false
                    },
                    {
                        "url":  "https://api.alternative.me/fng/?limit=1",
                        "data_ok":  true,
                        "latency_ok":  true,
                        "json_ok":  true,
                        "http_ok":  true,
                        "category":  "sentiment",
                        "latency_ms":  850,
                        "error":  null,
                        "critical":  false,
                        "name":  "alternative_fng",
                        "healthy":  true
                    },
                    {
                        "url":  "https://hacker-news.firebaseio.com/v0/topstories.json",
                        "data_ok":  true,
                        "latency_ok":  true,
                        "json_ok":  true,
                        "http_ok":  true,
                        "category":  "ai",
                        "latency_ms":  1331,
                        "error":  null,
                        "critical":  false,
                        "name":  "hn_topstories",
                        "healthy":  true
                    }
                ],
    "healthy":  2,
    "timestamp":  "2026-06-22T18:30:09+08:00",
    "verdict":  "red",
    "total":  5,
    "score":  40,
    "critical_fails":  [
                           "okx_btc",
                           "binance_btc"
                       ],
    "action":  "block_alert"
}
