{
  "macro": {
    "GOLD": {
      "confidence": "high",
      "timestamp": "2026-05-09 05:06:45",
      "unit": "USD/oz",
      "source": "goldprice.org + Yahoo Finance (playwright)",
      "value": 4715.6
    },
    "VIX": {
      "source": "Yahoo Finance ^VIX (playwright)",
      "timestamp": "2026-05-09 05:06:45",
      "value": 17.19,
      "confidence": "high"
    },
    "OIL": {
      "timestamp": "2026-05-09 05:06:45",
      "source": "Yahoo Finance CL=F (playwright)",
      "unit": "USD/barrel (WTI)",
      "value": 94.68,
      "confidence": "high"
    }
  },
  "fear_and_greed": {
    "value": 38,
    "value_classification": "Fear",
    "timestamp": "2026-05-09 05:00:00",
    "source": "alternative.me (browser)",
    "confidence": "high"
  },
  "collection_version": "macro-playwright-v3",
  "timestamp": "2026-05-09 05:06:45",
  "crypto": {
    "BTC": {
      "price": 80188.95,
      "change_pct": 0.60,
      "timestamp": "2026-05-09 05:06:45",
      "raw": "Yahoo Finance BTC-USD",
      "confidence": "high",
      "source": "Yahoo_Finance (playwright)"
    },
    "ETH": {
      "price": 2308.68,
      "change_pct": 0.93,
      "timestamp": "2026-05-09 05:06:45",
      "raw": "Yahoo Finance ETH-USD",
      "confidence": "high",
      "source": "Yahoo_Finance (playwright)"
    },
    "SOL": {
      "price": 92.21,
      "change_pct": 4.84,
      "timestamp": "2026-05-09 05:06:45",
      "raw": "Yahoo Finance SOL-USD",
      "confidence": "high",
      "source": "Yahoo_Finance (playwright)"
    }
  }
}