{
  "timestamp": "2026-04-02T11:58:00Z",
  "source": "GitHub API",
  "query": "stars:>1000 pushed:>2026-03-30",
  "total": 9638,
  "items": [
    { "name": "awesome", "full_name": "sindresorhus/awesome", "stars": 451077, "forks": 33901, "language": null, "description": "Awesome lists about all kinds of interesting topics", "pushed_at": "2026-04-01T08:25:16Z" },
    { "name": "freeCodeCamp", "full_name": "freeCodeCamp/freeCodeCamp", "stars": 440507, "forks": 43959, "language": "TypeScript", "description": "freeCodeCamp.org's open-source codebase and curriculum", "pushed_at": "2026-04-02T10:53:22Z" },
    { "name": "free-programming-books", "full_name": "EbookFoundation/free-programming-books", "stars": 384867, "forks": 66083, "language": "Python", "description": "Freely available programming books", "pushed_at": "2026-03-31T21:15:26Z" },
    { "name": "developer-roadmap", "full_name": "kamranahmedse/developer-roadmap", "stars": 352043, "forks": 43862, "language": "TypeScript", "description": "Interactive roadmaps, guides and educational content for developers", "pushed_at": "2026-04-01T11:07:26Z" },
    { "name": "openclaw", "full_name": "openclaw/openclaw", "stars": 345454, "forks": 68650, "language": "TypeScript", "description": "Your own personal AI assistant. Any OS. Any Platform.", "pushed_at": "2026-04-02T11:57:16Z" },
    { "name": "awesome-python", "full_name": "vinta/awesome-python", "stars": 290227, "forks": 27553, "language": "Python", "description": "An opinionated list of Python frameworks, libraries, tools", "pushed_at": "2026-04-02T01:48:01Z" },
    { "name": "react", "full_name": "facebook/react", "stars": 244331, "forks": 50876, "language": "JavaScript", "description": "The library for web and native user interfaces", "pushed_at": "2026-04-02T11:21:05Z" },
    { "name": "linux", "full_name": "torvalds/linux", "stars": 226532, "forks": 61327, "language": "C", "description": "Linux kernel source tree", "pushed_at": "2026-03-31T21:33:48Z" },
    { "name": "Python", "full_name": "TheAlgorithms/Python", "stars": 219206, "forks": 50292, "language": "Python", "description": "All Algorithms implemented in Python", "pushed_at": "2026-04-02T06:46:58Z" },
    { "name": "tensorflow", "full_name": "tensorflow/tensorflow", "stars": 194438, "forks": 75260, "language": "C++", "description": "An Open Source Machine Learning Framework for Everyone", "pushed_at": "2026-04-02T11:56:26Z" },
    { "name": "vscode", "full_name": "microsoft/vscode", "stars": 183315, "forks": 38896, "language": "TypeScript", "description": "Visual Studio Code", "pushed_at": "2026-04-02T11:34:35Z" },
    { "name": "AutoGPT", "full_name": "Significant-Gravitas/AutoGPT", "stars": 183058, "forks": 46222, "language": "Python", "description": "AutoGPT is the vision of accessible AI for everyone", "pushed_at": "2026-04-02T11:58:24Z" },
    { "name": "n8n", "full_name": "n8n-io/n8n", "stars": 182137, "forks": 56402, "language": "TypeScript", "description": "Fair-code workflow automation platform with native AI capabilities", "pushed_at": "2026-04-02T11:54:16Z" },
    { "name": "flutter", "full_name": "flutter/flutter", "stars": 175798, "forks": 30207, "language": "Dart", "description": "Flutter makes it easy and fast to build beautiful apps", "pushed_at": "2026-04-02T07:24:34Z" }
  ]
}
