{
  "date": "2026-04-21",
  "time": "17:30 GMT+8",
  "top_repositories": [
    {
      "rank": 1,
      "name": "Fincept-Corporation/FinceptTerminal",
      "stars": 10583,
      "language": "Python",
      "description": "Finance application with advanced market analytics and investment research tools",
      "stars_today": 3109
    },
    {
      "rank": 2,
      "name": "ruvnet/RuView",
      "stars": 48566,
      "language": "Rust",
      "description": "WiFi DensePose turns commodity WiFi signals into real-time human pose estimation",
      "stars_today": 713
    },
    {
      "rank": 3,
      "name": "thunderbird/thunderbolt",
      "stars": 3048,
      "language": "TypeScript",
      "description": "AI You Control - Choose your models. Own your data. Eliminate vendor lock-in.",
      "stars_today": 675
    },
    {
      "rank": 4,
      "name": "paperless-ngx/paperless-ngx",
      "stars": 39615,
      "language": "Python",
      "description": "Community-supported supercharged document management system",
      "stars_today": 606
    },
    {
      "rank": 5,
      "name": "koala73/worldmonitor",
      "stars": 50644,
      "language": "TypeScript",
      "description": "Real-time global intelligence dashboard with AI-powered news aggregation",
      "stars_today": 316
    }
  ],
  "source": "https://github.com/trending"
}