{
  "timestamp": "2026-04-27 11:06:51",
  "macro": {
    "VIX": {
      "confidence": "high",
      "value": 18.71,
      "raw": "{\"chart\":{\"result\":[{\"meta\":{\"currency\":\"USD\",\"symbol\":\"^VIX\",\"exchangeName\":\"CXI\",\"fullExchangeName",
      "source": "Yahoo_Finance_VIX",
      "timestamp": "2026-04-27 11:06:28"
    },
    "OIL": {
      "confidence": "high",
      "value": 95.27,
      "raw_len": 414622,
      "unit": "USD/barrel (WTI)",
      "timestamp": "2026-04-27 11:06:28",
      "source": "tradingeconomics.com"
    },
    "GOLD": {
      "confidence": "high",
      "value": 4722.2,
      "raw_len": 60726,
      "unit": "USD/oz",
      "timestamp": "2026-04-27 11:06:28",
      "source": "kitco.com"
    }
  },
  "source": "hourly-price-collector",
  "crypto": {
    "BTC": {
      "confidence": "high",
      "price": 79184.74,
      "raw": "{\"USD\":79184.74}",
      "source": "CryptoCompare_API",
      "timestamp": "2026-04-27 11:06:28"
    },
    "SOL": {
      "confidence": "high",
      "price": 87.85,
      "raw": "{\"USD\":87.85}",
      "source": "CryptoCompare_API",
      "timestamp": "2026-04-27 11:06:28"
    },
    "ETH": {
      "confidence": "high",
      "price": 2393.76,
      "raw": "{\"USD\":2393.76}",
      "source": "CryptoCompare_API",
      "timestamp": "2026-04-27 11:06:28"
    }
  }
}
